phjobs/__init__.py
phjobs/job1_hospital_mapping/__init__.py
phjobs/job1_hospital_mapping/phjob.py
phjobs/job1_hospital_mapping/phmain.py
phjobs/job2_product_mapping/__init__.py
phjobs/job2_product_mapping/phjob.py
phjobs/job2_product_mapping/phmain.py
phjobs/job3_data_adding/__init__.py
phjobs/job3_data_adding/phjob.py
phjobs/job3_data_adding/phmain.py
phjobs/job4_panel/__init__.py
phjobs/job4_panel/phjob.py
phjobs/job4_panel/phmain.py
phjobs/job5_max/__init__.py
phjobs/job5_max/phjob.py
phjobs/job5_max/phmain.py
phjobs/test1/__init__.py
phjobs/test1/phjob.py
phjobs/test1/phmain.py
phjobs/test2/__init__.py
phjobs/test2/phjob.py
phjobs/test2/phmain.py
phMaxJobs-0.1.3.dist-info/METADATA
phMaxJobs-0.1.3.dist-info/WHEEL
phMaxJobs-0.1.3.dist-info/top_level.txt
phMaxJobs-0.1.3.dist-info/RECORD
