Metadata-Version: 2.1
Name: phMaxJobs
Version: 0.1.3
Summary: pharbers dag scheduler config
Home-page: UNKNOWN
Author: Alfred Yang
Author-email: alfredyang@pharbers.com
License: UNKNOWN
Platform: UNKNOWN
Classifier: License :: OSI Approved :: MIT License
Classifier: Operating System :: OS Independent
Requires-Python: >=2.7
